lassie/__init__.py
lassie/api.py
lassie/compat.py
lassie/core.py
lassie/exceptions.py
lassie/utils.py
lassie/filters/__init__.py
lassie/filters/apple.py
lassie/filters/generic.py
lassie/filters/social.py
lassie/filters/oembed/__init__.py
lassie/filters/oembed/providers.py
lassie-0.11.9.dist-info/AUTHORS.rst
lassie-0.11.9.dist-info/LICENSE
lassie-0.11.9.dist-info/METADATA
lassie-0.11.9.dist-info/WHEEL
lassie-0.11.9.dist-info/top_level.txt
lassie-0.11.9.dist-info/RECORD
