Metadata-Version: 2.1
Name: lassie
Version: 0.11.9
Summary: Lassie is a Python library for retrieving basic content from websites
Home-page: https://github.com/michaelhelmick/lassie/tree/master
Author: Mike Helmick
Author-email: me@michaelhelmick.com
License: The MIT License
Requires-Dist: requests (<3.0.0,>=2.18.4)
Requires-Dist: beautifulsoup4 (<4.10.0,>=4.9.0)
Requires-Dist: html5lib (==1.0b10)
Requires-Dist: python-oembed
